{ "box" : 
[
    { "w":15, "h":25, "d":15, "tl":15.25, "f":1, "items":
        [

{ "i":0, "w":10, "h":7, "d":3, "x":0, "y":0, "z":0, "r":1 }
,
{ "i":1, "w":2, "h":7, "d":3, "x":0, "y":0, "z":3, "r":0 }
        ]
    }
    ,

    { "w":20, "h":15 , "d":15, "tl":25.25, "f":2, "items":
        [

{ "i":0, "w":10, "h":7, "d":3, "x":0, "y":0, "z":0, "r":1 }
,
{ "i":1, "w":2, "h":7, "d":3, "x":0, "y":0, "z":3, "r":0 }
,
{ "i":2, "w":2, "h":7, "d":3, "x":0, "y":0, "z":6, "r":0 }
,
{ "i":3, "w":2, "h":7, "d":3, "x":0, "y":0, "z":9, "r":0 }
,
{ "i":4, "w":2, "h":7, "d":3, "x":0, "y":0, "z":12, "r":0 }

        ]
    }
    ,

    { "w":2000, "h":2000, "d":2000, "tl":35.25, "f":3, "items":
        [

{ "i":0, "w":100, "h":70, "d":30, "x":0, "y":0, "z":0, "r":1 }
,
{ "i":1, "w":20, "h":70, "d":30, "x":0, "y":0, "z":30, "r":0 }

        ]
    } 
	 ,

    { "w":2000, "h":2000, "d":2000, "tl":35.25, "f":3, "items":
        [
        ]
    } 
	 ,

    { "w":2000, "h":2000, "d":2000, "tl":35.25, "f":3, "items":
        [
        ]
    } 
]
}